MyPy2sum/__init__.py
MyPy2sum-0.0.4.dist-info/DESCRIPTION.rst
MyPy2sum-0.0.4.dist-info/METADATA
MyPy2sum-0.0.4.dist-info/RECORD
MyPy2sum-0.0.4.dist-info/WHEEL
MyPy2sum-0.0.4.dist-info/metadata.json
MyPy2sum-0.0.4.dist-info/top_level.txt
