Metadata-Version: 2.0
Name: MyPy2sum
Version: 0.0.4
Summary: For addition of two numbers
Home-page: UNKNOWN
Author: harish r
Author-email: harish.r@imailt.com
License: UNKNOWN
Platform: UNKNOWN
Classifier: Programming Language :: Python :: 3
Classifier: License :: OSI Approved :: MIT License
Classifier: Operating System :: OS Independent
